scrape_google_images/__init__.py
scrape_google_images/image_scraper.py
scrape_google_images-1.0.2.dist-info/LICENSE
scrape_google_images-1.0.2.dist-info/METADATA
scrape_google_images-1.0.2.dist-info/WHEEL
scrape_google_images-1.0.2.dist-info/top_level.txt
scrape_google_images-1.0.2.dist-info/RECORD
