Metadata-Version: 2.1
Name: scrape_google_images
Version: 1.0.2
Summary: A python package to scrape images from Google Images.
Author-email: Ritik Pradhan <pradhanr@mailfence.com>
Project-URL: Homepage, https://github.com/pradhan-ritik/Scrape-Google-Images
Project-URL: Issues, https://github.com/pradhan-ritik/Scrape-Google-Images/issues
Classifier: Programming Language :: Python :: 3
Classifier: License :: OSI Approved :: MIT License
Classifier: Operating System :: OS Independent
Requires-Python: >=3.10
License-File: LICENSE
Requires-Dist: pillow
Requires-Dist: requests
